test_geometry/__init__.py
test_geometry/planimetry.py
test_geometry/stereometry.py
test_geometry-0.0.1.dist-info/LICENSE
test_geometry-0.0.1.dist-info/METADATA
test_geometry-0.0.1.dist-info/WHEEL
test_geometry-0.0.1.dist-info/top_level.txt
test_geometry-0.0.1.dist-info/RECORD
