Metadata-Version: 2.1
Name: test_geometry
Version: 0.0.1
Summary: Package for testing pip uploading
Author-email: Andrey Bessalov <author@example.com>
Project-URL: Homepage, https://github.com/abessalov/test_geometry
Classifier: Programming Language :: Python :: 3
Classifier: License :: OSI Approved :: MIT License
Classifier: Operating System :: OS Independent
Requires-Python: >=3.7
License-File: LICENSE
